matricity/__init__.py
matricity/matricity.py
matricity-0.1.0.dist-info/LICENSE
matricity-0.1.0.dist-info/METADATA
matricity-0.1.0.dist-info/WHEEL
matricity-0.1.0.dist-info/top_level.txt
matricity-0.1.0.dist-info/RECORD
