Metadata-Version: 2.1
Name: matricity
Version: 0.1.0
Summary: Embedded domain-specific library for implicitly and explicitly encoding functions as matrices that operate on domains of one-hot vectors.
Author: Andrei Lapets
Author-email: a@lapets.io
License: MIT
Project-URL: Repository, https://github.com/reity/matricity
Project-URL: Documentation, https://matricity.readthedocs.io
Requires-Python: >=3.7
License-File: LICENSE
Provides-Extra: docs
Requires-Dist: toml~=0.10.2; extra == "docs"
Requires-Dist: sphinx~=5.0; extra == "docs"
Requires-Dist: sphinx-rtd-theme~=2.0.0; extra == "docs"
Requires-Dist: sphinx-autodoc-typehints~=1.23.0; extra == "docs"
Provides-Extra: test
Requires-Dist: pytest~=7.4; python_version < "3.12" and extra == "test"
Requires-Dist: pytest~=8.2; python_version >= "3.12" and extra == "test"
Requires-Dist: pytest-cov~=4.1; python_version < "3.12" and extra == "test"
Requires-Dist: pytest-cov~=5.0; python_version >= "3.12" and extra == "test"
Provides-Extra: lint
Requires-Dist: pylint~=2.17.0; python_version < "3.12" and extra == "lint"
Requires-Dist: pylint~=3.2.0; python_version >= "3.12" and extra == "lint"
Provides-Extra: coveralls
Requires-Dist: coveralls~=4.0; extra == "coveralls"
Provides-Extra: publish
Requires-Dist: build~=0.10; extra == "publish"
Requires-Dist: twine~=4.0; extra == "publish"
